[
  {
    "wine_name": "AMARONE, LA BASTIA",
    "page_url": "https://www.wineconnection.com.sg/products/ca-de-rocchi-la-bastia-amarone-della-valpolicella-veneto-italy",
    "image_url": null
  },
  {
    "wine_name": "INZOILIO BIANCO, COLOSI",
    "page_url": "https://www.bottleshop.com/products/14249261/colosi-salina-bianco-2024",
    "image_url": null
  },
  {
    "wine_name": "VILLA ANTINORI BIANCO, VILLA ANTINORI",
    "page_url": "https://www.antinori.it/en/vino/villa-antinori-bianco-en/",
    "image_url": null
  },
  {
    "wine_name": "TREBBIANO, CATALDI MADONNA",
    "page_url": "https://cataldimadonna.com/product/trebbiano-d-abruzzo/",
    "image_url": null
  },
  {
    "wine_name": "PASSERINA, IL CONTE",
    "page_url": "https://www.vinello.co.uk/ceppo-marche-passerina-igp-il-conte-villa-prandone",
    "image_url": null
  },
  {
    "wine_name": "PISA VERMENTINO COLOMBANA",
    "page_url": "https://www.villasofiawine.com/product/colombana-igt-terre-di-pisa-hills/",
    "image_url": null
  },
  {
    "wine_name": "VERNACCIA TERRE TUFI, TERUZZI",
    "page_url": "https://www.palmbay.com/wines/teruzzi/teruzzi-terre-di-tufi-toscana-bianco-igt/",
    "image_url": null
  },
  {
    "wine_name": "VINO NOBILE, POLIZIANO",
    "page_url": "https://www.wine.com/product/poliziano-vino-nobile-di-montepulciano-2021/2028495",
    "image_url": null
  },
  {
    "wine_name": "BAROLO, TERREDDAVINO",
    "page_url": "https://www.saq.com/en/15192279",
    "image_url": null
  },
  {
    "wine_name": "BRUNELLO , SANT'ANTIMO",
    "page_url": "https://www.wine.com/product/molino-di-santantimo-brunello-di-montalcino-2016/973625",
    "image_url": null
  },
  {
    "wine_name": "MONTEPULCIANO, EMIDIO PEPE",
    "page_url": "https://www.emidiopepe.com/en/",
    "image_url": null
  },
  {
    "wine_name": "SANGIOVESE, SANTA CRISTINA",
    "page_url": "http://www.santacristina.wine/en/product/vermentino-bottle/",
    "image_url": null
  },
  {
    "wine_name": "FRANCIACORTA ANNAMARIA CLEMENTI, CA' DEL BOSCO",
    "page_url": "https://www.cadelbosco.com/en/wine-categories/franciacorta-wines/annamaria-clementi/",
    "image_url": null
  },
  {
    "wine_name": "AMARONE, TOMASSI",
    "page_url": "https://shop.allamarone.com/wine/amarone-docg-classico-tommasi/",
    "image_url": null
  },
  {
    "wine_name": "AMARONE, SPERI",
    "page_url": "https://www.speri.com/en/wines/amarone/",
    "image_url": null
  },
  {
    "wine_name": "AMARONE, BUGLIONI",
    "page_url": "https://buglioni.it/en/shop/amarone-riserva-testedure/",
    "image_url": null
  },
  {
    "wine_name": "AMARONE, ALLEGRINI",
    "page_url": "https://allegrini.it/en/wines/amarone-della-valpolicella-classico-allegrini/",
    "image_url": null
  },
  {
    "wine_name": "AMARONE, BERTANI",
    "page_url": "https://www.bertani.net/wines/tradition/amarone-della-valpolicella-classico/",
    "image_url": null
  },
  {
    "wine_name": "VALPOLICELLA SUPERIORE, DAL FORNO",
    "page_url": "https://bottleofitaly.com/en-us/products/amarone-della-valpolicella-docg-dal-forno-romano",
    "image_url": null
  },
  {
    "wine_name": "AMARONE, DAL FORNO*",
    "page_url": "https://bottleofitaly.com/en-us/products/amarone-della-valpolicella-docg-dal-forno-romano",
    "image_url": null
  }
]